carlo_distributions/Binomialdistribution.py
carlo_distributions/Gaussiandistribution.py
carlo_distributions/Generaldistribution.py
carlo_distributions/__init__.py
carlo_distributions-0.0.1.dist-info/LICENSE.txt
carlo_distributions-0.0.1.dist-info/METADATA
carlo_distributions-0.0.1.dist-info/WHEEL
carlo_distributions-0.0.1.dist-info/top_level.txt
carlo_distributions-0.0.1.dist-info/RECORD
