Metadata-Version: 2.1
Name: carlo_distributions
Version: 0.0.1
Summary: Basic Gaussian and Binomial distributions classes
Home-page: UNKNOWN
Author: John Carlo Roberto
Author-email: john.devera.roberto@gmail.com
License: UNKNOWN
Platform: UNKNOWN
License-File: LICENSE.txt
